<?xml version="1.0" encoding="UTF-8"?>
<?xml-stylesheet type='text/xsl' href='_ConversionReport_Files/ConversionReport.xslt'?>
<UpgradeLog>
  <Properties>
    <Property Name="Project" Value="HelloWorld" />
    <Property Name="Project File" Value="C:\Users\wandrus.OVERSITETECH\Documents\GitHub\SQLCLR-Library\SQLCLR\HelloWorld\HelloWorld.csproj" />
    <Property Name="Date" Value="Tuesday, May 07, 2013" />
    <Property Name="Time" Value="1:38 PM" />
  </Properties>
  <Event ErrorLevel="0" Project="C:\Users\wandrus.OVERSITETECH\Documents\GitHub\SQLCLR-Library\SQLCLR\HelloWorld\HelloWorld.csproj" Source="..\HelloWorld.csproj" Description="Project was successfully converted: 'C:\Users\wandrus.OVERSITETECH\Documents\GitHub\SQLCLR-Library\SQLCLR\HelloWorld\HelloWorld.csproj' to 'C:\Users\wandrus.OVERSITETECH\Documents\GitHub\SQLCLR-Library\SQLCLR\HelloWorld\HelloWorld.sqlproj'" />
  <Event ErrorLevel="3" Project="C:\Users\wandrus.OVERSITETECH\Documents\GitHub\SQLCLR-Library\SQLCLR\HelloWorld\HelloWorld.csproj" Source="..\HelloWorld.csproj" Description="Converted" />
</UpgradeLog>